stream_infer/__init__.py
stream_infer/algo.py
stream_infer/dispatcher/__init__.py
stream_infer/dispatcher/base.py
stream_infer/dispatcher/develop.py
stream_infer/dynamic.py
stream_infer/inference.py
stream_infer/log.py
stream_infer/model.py
stream_infer/player.py
stream_infer/producer/__init__.py
stream_infer/producer/_imageio.py
stream_infer/producer/_opencv.py
stream_infer/producer/_pyav.py
stream_infer/recorder.py
stream_infer/streamlit_.py
stream_infer/timer.py
stream_infer/util/__init__.py
stream_infer-0.6.7.dist-info/LICENSE
stream_infer-0.6.7.dist-info/METADATA
stream_infer-0.6.7.dist-info/WHEEL
stream_infer-0.6.7.dist-info/RECORD
