Metadata-Version: 2.3
Name: stream_infer
Version: 0.6.7
Summary: Video streaming inference framework, integrating image algorithms and models for real-time/offline video structuring
License: Apache-2.0
Keywords: machine-learning,deep-learning,vision,ML,DL,AI,streaming framework,DeepStream,video-processing,inference
Author: ZaiGie
Author-email: jokerwho@yeah.net
Maintainer: ZaiGie
Maintainer-email: jokerwho@yeah.net
Requires-Python: >=3.8.1,<3.13.0
Classifier: Development Status :: 4 - Beta
Classifier: Intended Audience :: Developers
Classifier: Intended Audience :: Education
Classifier: Intended Audience :: Science/Research
Classifier: License :: OSI Approved :: Apache Software License
Classifier: Operating System :: MacOS
Classifier: Operating System :: Microsoft :: Windows
Classifier: Operating System :: POSIX :: Linux
Classifier: Programming Language :: Python :: 3
Classifier: Programming Language :: Python :: 3.9
Classifier: Programming Language :: Python :: 3.10
Classifier: Programming Language :: Python :: 3.11
Classifier: Programming Language :: Python :: 3.12
Classifier: Programming Language :: Python :: 3 :: Only
Classifier: Programming Language :: Python :: 3.8
Classifier: Topic :: Scientific/Engineering
Classifier: Topic :: Scientific/Engineering :: Artificial Intelligence
Classifier: Topic :: Scientific/Engineering :: Image Recognition
Classifier: Topic :: Software Development
Classifier: Typing :: Typed
Provides-Extra: desktop
Provides-Extra: server
Requires-Dist: av (>=11.0.0)
Requires-Dist: loguru (>=0.6.0)
Requires-Dist: numpy (>=1.21.2)
Requires-Dist: opencv-python (==0.6.7) ; extra == "desktop"
Requires-Dist: opencv-python-headless (>=4.5.5.64)
Requires-Dist: pydantic (>=2.0.0)
Requires-Dist: streamlit (==0.6.7) ; extra == "server"
Requires-Dist: tqdm (>=4.62.3,<=4.66.1)
Requires-Dist: typing-extensions (>=4.5.0)
Project-URL: Documentation, https://github.com/zaigie/stream-infer/blob/main/README.md
Project-URL: Homepage, https://github.com/zaigie/stream-infer
Project-URL: Repository, https://github.com/zaigie/stream-infer
